LICENSE
README.md
pyproject.toml
setup.cfg
setup.py
prosuite/__init__.py
prosuite/data_model.py
prosuite/quality.py
prosuite/utils.py
prosuite/verification.py
prosuite.egg-info/PKG-INFO
prosuite.egg-info/SOURCES.txt
prosuite.egg-info/dependency_links.txt
prosuite.egg-info/requires.txt
prosuite.egg-info/top_level.txt
prosuite/datatypes/__init__.py
prosuite/datatypes/esri_geometry_type.py
prosuite/datatypes/expected_case.py
prosuite/datatypes/expected_string_difference.py
prosuite/datatypes/non_linear_segment_type.py
prosuite/datatypes/unique_strings_constraint.py
prosuite/factories/__init__.py
prosuite/factories/enums.py
prosuite/factories/issue_filters.py
prosuite/factories/quality_conditions.py
prosuite/factories/transformers.py
prosuite/generated/__init__.py
prosuite/generated/quality_test_pb2.py
prosuite/generated/quality_test_pb2.pyi
prosuite/generated/quality_test_pb2_grpc.py
prosuite/generated/quality_verification_ddx_pb2.py
prosuite/generated/quality_verification_ddx_pb2.pyi
prosuite/generated/quality_verification_ddx_pb2_grpc.py
prosuite/generated/quality_verification_service_pb2.py
prosuite/generated/quality_verification_service_pb2.pyi
prosuite/generated/quality_verification_service_pb2_grpc.py
prosuite/generated/shared_ddx_pb2.py
prosuite/generated/shared_ddx_pb2.pyi
prosuite/generated/shared_gdb_pb2.py
prosuite/generated/shared_gdb_pb2.pyi
prosuite/generated/shared_qa_pb2.py
prosuite/generated/shared_qa_pb2.pyi