Metadata-Version: 2.1
Name: prosuite
Version: 1.4.0.1
Summary: An API to configure quality assurance tests for geodata and execute quality verifications on a ProSuite Server
Home-page: https://dirageosystems.ch/prosuite/doc/api
Author: Dira GeoSystems
Author-email: programmers@dirageosystems.ch
License: MIT
Keywords: prosuite,gis,arcgis,geodata,spatial-data,quality,quality-assurance,qa,test
Classifier: Operating System :: OS Independent
Classifier: Programming Language :: Python :: 3
Classifier: Development Status :: 5 - Production/Stable
Classifier: License :: OSI Approved :: MIT License
License-File: LICENSE
Requires-Dist: lxml
Requires-Dist: grpcio>1.4.0
Requires-Dist: protobuf<5.0dev,>=4.21.6
